setup.py
newToolsNew00.egg-info/PKG-INFO
newToolsNew00.egg-info/SOURCES.txt
newToolsNew00.egg-info/dependency_links.txt
newToolsNew00.egg-info/entry_points.txt
newToolsNew00.egg-info/requires.txt
newToolsNew00.egg-info/top_level.txt
newUtils/__init__.py
newUtils/logger.py
newUtils/wechatRobot.py